amarantos/rank.py
amarantos/core/loaders.py
amarantos/core/schemas.py
amarantos/data/choices/diet/almonds.yaml
amarantos/data/choices/diet/alpha_lipoic_acid.yaml
amarantos/data/choices/diet/apple_cider_vinegar.yaml
amarantos/data/choices/diet/ashwagandha.yaml
amarantos/data/choices/diet/astaxanthin.yaml
amarantos/data/choices/diet/avocado.yaml
amarantos/data/choices/diet/b_vitamins_complex.yaml
amarantos/data/choices/diet/berberine.yaml
amarantos/data/choices/diet/betaine.yaml
amarantos/data/choices/diet/betaine_tmg.yaml
amarantos/data/choices/diet/blueberries.yaml
amarantos/data/choices/diet/cacao_flavanols.yaml
amarantos/data/choices/diet/calcium.yaml
amarantos/data/choices/diet/carnitine.yaml
amarantos/data/choices/diet/chlorella.yaml
amarantos/data/choices/diet/choline.yaml
amarantos/data/choices/diet/coffee.yaml
amarantos/data/choices/diet/collagen_peptides.yaml
amarantos/data/choices/diet/coq10.yaml
amarantos/data/choices/diet/creatine.yaml
amarantos/data/choices/diet/creatine_monohydrate.yaml
amarantos/data/choices/diet/cruciferous_vegetables.yaml
amarantos/data/choices/diet/curcumin_turmeric.yaml
amarantos/data/choices/diet/dark_chocolate.yaml
amarantos/data/choices/diet/dietary_fiber.yaml
amarantos/data/choices/diet/equol.yaml
amarantos/data/choices/diet/fatty_fish.yaml
amarantos/data/choices/diet/fermented_foods.yaml
amarantos/data/choices/diet/fiber.yaml
amarantos/data/choices/diet/fisetin.yaml
amarantos/data/choices/diet/garlic.yaml
amarantos/data/choices/diet/ginger.yaml
amarantos/data/choices/diet/glycine.yaml
amarantos/data/choices/diet/green_tea.yaml
amarantos/data/choices/diet/iron.yaml
amarantos/data/choices/diet/l_carnitine.yaml
amarantos/data/choices/diet/leafy_greens.yaml
amarantos/data/choices/diet/lion_s_mane_mushroom.yaml
amarantos/data/choices/diet/magnesium.yaml
amarantos/data/choices/diet/mct_oil.yaml
amarantos/data/choices/diet/melatonin.yaml
amarantos/data/choices/diet/mushrooms.yaml
amarantos/data/choices/diet/nad_precursors.yaml
amarantos-0.1.2.dist-info/METADATA
amarantos-0.1.2.dist-info/WHEEL
amarantos-0.1.2.dist-info/entry_points.txt
amarantos-0.1.2.dist-info/licenses/LICENSE
amarantos-0.1.2.dist-info/RECORD
