Metadata-Version: 2.4
Name: amarantos
Version: 0.1.2
Summary: Tips and tools for personal wellness and longevity
Project-URL: Repository, https://github.com/zkurtz/amarantos
Author-email: Zach Kurtz <zkurtz@gmail.com>
License-Expression: MIT
License-File: LICENSE
Requires-Python: >=3.13
Requires-Dist: attrs>=25.4
Requires-Dist: click>=8.3.1
Requires-Dist: dummio>=1.10.2
Requires-Dist: matplotlib>=3.10.8
Requires-Dist: numpy>=2.2.6
Requires-Dist: pre-commit>=4.0.1
Requires-Dist: ruamel-yaml>=0.19.1
